jerrybuild/__init__.py
jerrybuild/bottle.py
jerrybuild/build_queue.py
jerrybuild/job.py
jerrybuild/jobdef.py
jerrybuild/jobdef_manager.py
jerrybuild/main.py
jerrybuild/routes.py
jerrybuild/tools.py
jerrybuild/vacuum.py
jerrybuild/wsgi_server.py
jerrybuild/providers/__init__.py
jerrybuild/providers/generic.py
jerrybuild/providers/github.py
jerrybuild/providers/gogs.py
jerrybuild-1.0.0a0.data/data/lib/jerrybuild/jerrybuild.cfg.dist
jerrybuild-1.0.0a0.data/data/lib/jerrybuild/jerrybuild.service.dist
jerrybuild-1.0.0a0.data/data/lib/jerrybuild/static/css/index.css
jerrybuild-1.0.0a0.data/data/lib/jerrybuild/static/css/reset.css
jerrybuild-1.0.0a0.data/data/lib/jerrybuild/static/font-awesome/css/font-awesome.css
jerrybuild-1.0.0a0.data/data/lib/jerrybuild/static/font-awesome/css/font-awesome.min.css
jerrybuild-1.0.0a0.data/data/lib/jerrybuild/static/font-awesome/fonts/FontAwesome.otf
jerrybuild-1.0.0a0.data/data/lib/jerrybuild/static/font-awesome/fonts/fontawesome-webfont.eot
jerrybuild-1.0.0a0.data/data/lib/jerrybuild/static/font-awesome/fonts/fontawesome-webfont.svg
jerrybuild-1.0.0a0.data/data/lib/jerrybuild/static/font-awesome/fonts/fontawesome-webfont.ttf
jerrybuild-1.0.0a0.data/data/lib/jerrybuild/static/font-awesome/fonts/fontawesome-webfont.woff
jerrybuild-1.0.0a0.data/data/lib/jerrybuild/static/font-awesome/fonts/fontawesome-webfont.woff2
jerrybuild-1.0.0a0.data/data/lib/jerrybuild/static/img/logo.png
jerrybuild-1.0.0a0.data/data/lib/jerrybuild/views/base.tpl
jerrybuild-1.0.0a0.data/data/lib/jerrybuild/views/index.tpl
jerrybuild-1.0.0a0.data/data/lib/jerrybuild/views/job_definition.tpl
jerrybuild-1.0.0a0.data/data/lib/jerrybuild/views/job_shield.tpl
jerrybuild-1.0.0a0.data/data/lib/jerrybuild/views/job_status.tpl
jerrybuild-1.0.0a0.data/data/lib/jerrybuild/views/helpers/job_duration.tpl
jerrybuild-1.0.0a0.data/data/lib/jerrybuild/views/helpers/job_status.tpl
jerrybuild-1.0.0a0.dist-info/METADATA
jerrybuild-1.0.0a0.dist-info/RECORD
jerrybuild-1.0.0a0.dist-info/WHEEL
jerrybuild-1.0.0a0.dist-info/entry_points.txt
jerrybuild-1.0.0a0.dist-info/top_level.txt
